{
    "type": "object",
    "properties": {
        "resourceGroupName": {
            "required": true,
            "type": "string"
        },
        "webServiceName": {
            "required": true,
            "type": "string"
        },
        "region": {
            "required": true,
            "type": "string"
        },
        "subscriptionId": {
            "required": true,
            "type": "string"
        },
        "api_version": {
            "required": true,
            "type": "string"
        }
    }
}